[
  {
    "id": "01k93s7sjg75414p5j93c503kd",
    "name": "Veniam quas voluptates et.",
    "description": "Dolorem sunt qui ut molestiae corrupti. Tenetur et voluptas voluptates officia mollitia perspiciatis nisi voluptatibus. Est velit nihil praesentium quo quae.",
    "status": "done",
    "due_date": "2025-12-26",
    "created": {
      "human": "3 hours ago",
      "string": "2025-11-03T02:37:46+00:00"
    },
    "project": {
      "id": "01k93s7sf92fc8zwrc4d1m2wtp",
      "name": "Brakus LLC",
      "description": "Hatter went on in the lock, and to wonder what CAN have happened to you? Tell us all about it!' Last came a rumbling of little birds and beasts, as well as she fell past it. 'Well!' thought Alice to.",
      "created": {
        "human": "3 hours ago",
        "string": "2025-11-03T02:37:46+00:00"
      }
    },
    "assigned_to": {
      "id": "01k93s7sbjgmmwshckzxyst82t",
      "name": "Prof. Aurelia Shields",
      "email": {
        "address": "tony76@example.net",
        "verified": true
      },
      "created": {
        "human": "3 hours ago",
        "string": "2025-11-03T02:37:46+00:00"
      }
    }
  },
  {
    "id": "01k93s7sjmgs5aq44ycwp55a8b",
    "name": "Ipsa omnis.",
    "description": "Soluta id earum similique. Magni ut soluta aspernatur corporis neque. Expedita impedit eius debitis maiores.",
    "status": "todo",
    "due_date": "2025-11-04",
    "created": {
      "human": "3 hours ago",
      "string": "2025-11-03T02:37:46+00:00"
    },
    "project": {
      "id": "01k93s7sf92fc8zwrc4d1m2wtp",
      "name": "Brakus LLC",
      "description": "Hatter went on in the lock, and to wonder what CAN have happened to you? Tell us all about it!' Last came a rumbling of little birds and beasts, as well as she fell past it. 'Well!' thought Alice to.",
      "created": {
        "human": "3 hours ago",
        "string": "2025-11-03T02:37:46+00:00"
      }
    },
    "assigned_to": {
      "id": "01k93s7sax2zryk5ak4c4bcykz",
      "name": "Joelle Maggio",
      "email": {
        "address": "ckovacek@example.org",
        "verified": true
      },
      "created": {
        "human": "3 hours ago",
        "string": "2025-11-03T02:37:46+00:00"
      }
    }
  },
  {
    "id": "01k93s7sjrey137p7k1tc1prnv",
    "name": "Aut possimus quia quae.",
    "description": "Quas possimus ut impedit ad et illo exercitationem labore. Est eum et cumque consectetur facere aliquam eos quam. Laboriosam optio non rem eveniet eveniet vel ipsa.",
    "status": "in_progress",
    "due_date": "2025-11-08",
    "created": {
      "human": "3 hours ago",
      "string": "2025-11-03T02:37:46+00:00"
    },
    "project": {
      "id": "01k93s7sf92fc8zwrc4d1m2wtp",
      "name": "Brakus LLC",
      "description": "Hatter went on in the lock, and to wonder what CAN have happened to you? Tell us all about it!' Last came a rumbling of little birds and beasts, as well as she fell past it. 'Well!' thought Alice to.",
      "created": {
        "human": "3 hours ago",
        "string": "2025-11-03T02:37:46+00:00"
      }
    },
    "assigned_to": {
      "id": "01k93s7sc35phmmx6zw6ynwj1f",
      "name": "Deron Hickle",
      "email": {
        "address": "denis01@example.com",
        "verified": true
      },
      "created": {
        "human": "3 hours ago",
        "string": "2025-11-03T02:37:46+00:00"
      }
    }
  },
  {
    "id": "01k93s7sk03x1z76gj2nyfj49d",
    "name": "Incidunt porro aut fugit.",
    "description": "Doloremque aspernatur quo est libero dicta tempora ea. Maxime qui odit id qui quo. Fugit dolorum in ut ut nulla cupiditate. Numquam eos magni neque cum consequuntur nisi.",
    "status": "done",
    "due_date": null,
    "created": {
      "human": "3 hours ago",
      "string": "2025-11-03T02:37:46+00:00"
    },
    "project": {
      "id": "01k93s7sf92fc8zwrc4d1m2wtp",
      "name": "Brakus LLC",
      "description": "Hatter went on in the lock, and to wonder what CAN have happened to you? Tell us all about it!' Last came a rumbling of little birds and beasts, as well as she fell past it. 'Well!' thought Alice to.",
      "created": {
        "human": "3 hours ago",
        "string": "2025-11-03T02:37:46+00:00"
      }
    },
    "assigned_to": {
      "id": "01k93s7sbpgnfq80zrjvgqejxd",
      "name": "Logan Sanford",
      "email": {
        "address": "veichmann@example.com",
        "verified": true
      },
      "created": {
        "human": "3 hours ago",
        "string": "2025-11-03T02:37:46+00:00"
      }
    }
  },
  {
    "id": "01k93s7sk5xf1c3v6es66pw045",
    "name": "Ut vero ipsum.",
    "description": "Non dicta animi non ea praesentium incidunt dicta. Ut itaque sed aut neque aut nulla. Ut ullam laborum eius veniam sed fuga. Facere dignissimos quod asperiores ipsa quasi non.",
    "status": "todo",
    "due_date": null,
    "created": {
      "human": "3 hours ago",
      "string": "2025-11-03T02:37:46+00:00"
    },
    "project": {
      "id": "01k93s7sf92fc8zwrc4d1m2wtp",
      "name": "Brakus LLC",
      "description": "Hatter went on in the lock, and to wonder what CAN have happened to you? Tell us all about it!' Last came a rumbling of little birds and beasts, as well as she fell past it. 'Well!' thought Alice to.",
      "created": {
        "human": "3 hours ago",
        "string": "2025-11-03T02:37:46+00:00"
      }
    },
    "assigned_to": {
      "id": "01k93s7sc35phmmx6zw6ynwj1f",
      "name": "Deron Hickle",
      "email": {
        "address": "denis01@example.com",
        "verified": true
      },
      "created": {
        "human": "3 hours ago",
        "string": "2025-11-03T02:37:46+00:00"
      }
    }
  }
]
